expediagroup/sdk/core/__init__.py
expediagroup/sdk/core/client/__init__.py
expediagroup/sdk/core/client/api.py
expediagroup/sdk/core/client/auth_client.py
expediagroup/sdk/core/client/expediagroup_auth_client.py
expediagroup/sdk/core/client/rapid_auth_client.py
expediagroup/sdk/core/configuration/__init__.py
expediagroup/sdk/core/configuration/auth_config.py
expediagroup/sdk/core/configuration/client_config.py
expediagroup/sdk/core/constant/__init__.py
expediagroup/sdk/core/constant/body.py
expediagroup/sdk/core/constant/constant.py
expediagroup/sdk/core/constant/header.py
expediagroup/sdk/core/constant/log.py
expediagroup/sdk/core/constant/message.py
expediagroup/sdk/core/constant/url.py
expediagroup/sdk/core/model/__init__.py
expediagroup/sdk/core/model/api.py
expediagroup/sdk/core/model/authentication.py
expediagroup/sdk/core/model/error.py
expediagroup/sdk/core/model/rapid_auth.py
expediagroup/sdk/core/model/exception/client.py
expediagroup/sdk/core/model/exception/expediagroup.py
expediagroup/sdk/core/model/exception/service.py
expediagroup/sdk/core/util/__init__.py
expediagroup/sdk/core/util/log.py
expediagroup_sdk_python_core-3.3.0.dist-info/METADATA
expediagroup_sdk_python_core-3.3.0.dist-info/WHEEL
expediagroup_sdk_python_core-3.3.0.dist-info/top_level.txt
expediagroup_sdk_python_core-3.3.0.dist-info/RECORD
