Metadata-Version: 2.1
Name: expediagroup-sdk-python-core
Version: 3.3.0
Summary: Expedia Group SDK Core Library for Python
Home-page: https://github.com/ExpediaGroup/expediagroup-sdk-python
Author: Expedia Group
Author-email: oss@expediagroup.com
License: Apache License, Version 2.0
Classifier: Development Status :: 3 - Alpha
Classifier: Programming Language :: Python
Classifier: Programming Language :: Python :: 3 :: Only
Classifier: Programming Language :: Python :: 3
Classifier: Programming Language :: Python :: 3.8
Classifier: Programming Language :: Python :: 3.9
Classifier: Programming Language :: Python :: 3.10
Classifier: Programming Language :: Python :: 3.11
Classifier: License :: OSI Approved :: MIT License
Requires-Python: >=3.8
Requires-Dist: pydantic
Requires-Dist: uri
Requires-Dist: requests
Requires-Dist: python-dateutil
